LICENSE
MANIFEST.in
README.md
README.rst
requirements.txt
setup.py
django_janyson.egg-info/PKG-INFO
django_janyson.egg-info/SOURCES.txt
django_janyson.egg-info/dependency_links.txt
django_janyson.egg-info/requires.txt
django_janyson.egg-info/top_level.txt
janyson/__init__.py
janyson/apps.py
janyson/decorators.py
janyson/descriptors.py
janyson/fields.py
janyson/forms.py
janyson/options.py
janyson/utils.py
janyson/validators.py
janyson/locale/en/LC_MESSAGES/django.mo
janyson/locale/en/LC_MESSAGES/django.po
janyson/locale/ru/LC_MESSAGES/django.mo
janyson/locale/ru/LC_MESSAGES/django.po