Metadata-Version: 1.1
Name: django-janyson
Version: 0.1.0
Summary: Virtual model fields that are transparently mapped to Postgres jsonb
Home-page: https://github.com/un-def/django-janyson
Author: un.def
Author-email: un.def@ya.ru
License: BSD License
Platform: UNKNOWN
Classifier: Environment :: Web Environment
Classifier: Framework :: Django
Classifier: Intended Audience :: Developers
Classifier: License :: OSI Approved :: BSD License
Classifier: Operating System :: OS Independent
Classifier: Programming Language :: Python
Classifier: Programming Language :: Python :: 2
Classifier: Programming Language :: Python :: 3
Classifier: Topic :: Internet :: WWW/HTTP
Classifier: Topic :: Internet :: WWW/HTTP :: Dynamic Content
